emodel_generalisation/__init__.py
emodel_generalisation/adaptation.py
emodel_generalisation/bluecellulab_evaluator.py
emodel_generalisation/cli.py
emodel_generalisation/exemplars.py
emodel_generalisation/information.py
emodel_generalisation/mcmc.py
emodel_generalisation/morph_utils.py
emodel_generalisation/select.py
emodel_generalisation/utils.py
emodel_generalisation/validation.py
emodel_generalisation/version.py
emodel_generalisation/model/__init__.py
emodel_generalisation/model/access_point.py
emodel_generalisation/model/bpopt.py
emodel_generalisation/model/ecodes.py
emodel_generalisation/model/evaluation.py
emodel_generalisation/model/modifiers.py
emodel_generalisation/model/nexus_converter.py
emodel_generalisation/tasks/__init__.py
emodel_generalisation/tasks/utils.py
emodel_generalisation/tasks/workflow.py
emodel_generalisation/templates/cell_template_neurodamus.jinja2
emodel_generalisation/templates/cell_template_neurodamus_placeholder.jinja2
emodel_generalisation-0.2.14.dist-info/AUTHORS.md
emodel_generalisation-0.2.14.dist-info/LICENSE.txt
emodel_generalisation-0.2.14.dist-info/METADATA
emodel_generalisation-0.2.14.dist-info/WHEEL
emodel_generalisation-0.2.14.dist-info/entry_points.txt
emodel_generalisation-0.2.14.dist-info/top_level.txt
emodel_generalisation-0.2.14.dist-info/RECORD
