Metadata-Version: 2.1
Name: emodel-generalisation
Version: 0.2.14
Summary: Generalisation of neuronal electrical models with MCMC
Home-page: https://emodel-generalisation.readthedocs.io
Author: Blue Brain Project, EPFL
License: GNU General Public License v3.0
Project-URL: Tracker, https://github.com/BlueBrain/emodel-generalisation/issues
Project-URL: Source, https://github.com/BlueBrain/emodel-generalisation
Classifier: Development Status :: 2 - Pre-Alpha
Classifier: Intended Audience :: Education
Classifier: Intended Audience :: Science/Research
Classifier: Programming Language :: Python
Classifier: Programming Language :: Python :: 3
Classifier: Programming Language :: Python :: 3.8
Classifier: Programming Language :: Python :: 3.9
Classifier: Programming Language :: Python :: 3.10
Classifier: Programming Language :: Python :: 3.11
Classifier: Topic :: Scientific/Engineering :: Bio-Informatics
Requires-Python: >=3.8
License-File: LICENSE.txt
License-File: AUTHORS.md
Requires-Dist: matplotlib >=3.6.2
Requires-Dist: morphio >=3.3.4
Requires-Dist: neurom >=3.2.2
Requires-Dist: numpy >=1.23.5
Requires-Dist: pandas >=1.5.3
Requires-Dist: scipy >=1.10.0
Requires-Dist: seaborn >=0.12.2
Requires-Dist: bluepyopt >=1.13.196
Requires-Dist: neuron >=8.2.2
Requires-Dist: morph-tool >=2.9.1
Requires-Dist: luigi-tools >=0.3.3
Requires-Dist: diameter-synthesis >=0.5.4
Requires-Dist: scikit-learn >=1.1.3
Requires-Dist: shap >=0.41.0
Requires-Dist: xgboost <2,>=1.7.5
Requires-Dist: pyyaml >=6
Requires-Dist: datareuse >=0.0.3
Requires-Dist: bluepyparallel >=0.2.2
Requires-Dist: bluecellulab >=2.6.11
Requires-Dist: voxcell >=3.1.5
Requires-Dist: efel >=5.5.5
Provides-Extra: docs
Requires-Dist: docutils <0.21 ; extra == 'docs'
Requires-Dist: m2r2 ; extra == 'docs'
Requires-Dist: sphinx ; extra == 'docs'
Requires-Dist: sphinx-bluebrain-theme ; extra == 'docs'
Provides-Extra: test
Requires-Dist: pytest >=7 ; extra == 'test'
Requires-Dist: pytest-console-scripts >=1.3 ; extra == 'test'
Requires-Dist: pytest-cov >=3 ; extra == 'test'
Requires-Dist: pytest-html >=2 ; extra == 'test'
Requires-Dist: pytest-click >=1.1.0 ; extra == 'test'
